eCHORDpost/IPF_V1.py
eCHORDpost/Symetry.py
eCHORDpost/Xallo.py
echordpost-0.1.3.dist-info/LICENSE
echordpost-0.1.3.dist-info/METADATA
echordpost-0.1.3.dist-info/WHEEL
echordpost-0.1.3.dist-info/RECORD
